README.md
setup.py
helpdeskbot/__init__.py
helpdeskbot/__main__.py
helpdeskbot.egg-info/PKG-INFO
helpdeskbot.egg-info/SOURCES.txt
helpdeskbot.egg-info/dependency_links.txt
helpdeskbot.egg-info/entry_points.txt
helpdeskbot.egg-info/not-zip-safe
helpdeskbot.egg-info/requires.txt
helpdeskbot.egg-info/top_level.txt