Metadata-Version: 1.2
Name: helpdeskbot
Version: 2.2.1
Summary: Discord utility bot for DevDungeon.com
Home-page: https://github.com/DevDungeon/HelpDeskBot
Author: John Leon
Author-email: nanodano@devdungeon.com
License: GPL-3.0
Platform: UNKNOWN
Requires-Python: >=3.7
